noiz/__init__.py
noiz/__main__.py
noiz/app.py
noiz/cli.py
noiz/database.py
noiz/exceptions.py
noiz/globals.py
noiz/routes.py
noiz/settings.py
noiz/validation_helpers.py
noiz/api/__init__.py
noiz/api/beamforming.py
noiz/api/beamforming_plotting.py
noiz/api/component.py
noiz/api/component_pair.py
noiz/api/crosscorrelations.py
noiz/api/database_helpers.py
noiz/api/datachunk.py
noiz/api/datachunk_plotting.py
noiz/api/event_detection.py
noiz/api/helpers.py
noiz/api/ppsd.py
noiz/api/processing_config.py
noiz/api/psd_plotting.py
noiz/api/qc.py
noiz/api/soh.py
noiz/api/soh_plotting.py
noiz/api/stacking.py
noiz/api/timeseries.py
noiz/api/timespan.py
noiz/models/__init__.py
noiz/models/beamforming.py
noiz/models/component.py
noiz/models/component_pair.py
noiz/models/crosscorrelation.py
noiz/models/custom_db_types.py
noiz/models/datachunk.py
noiz/models/event_detection.py
noiz/models/mixins.py
noiz/models/ppsd.py
noiz/models/processing_params.py
noiz/models/qc.py
noiz/models/soh.py
noiz/models/stacking.py
noiz/models/timeseries.py
noiz/models/timespan.py
noiz/models/type_aliases.py
noiz/processing/__init__.py
noiz/processing/beamforming.py
noiz/processing/component.py
noiz/processing/component_pair.py
noiz/processing/configs.py
noiz/processing/crosscorrelations.py
noiz/processing/datachunk.py
noiz/processing/datachunk_processing.py
noiz/processing/event_detection.py
noiz/processing/io.py
noiz/processing/miniseed_helpers.py
noiz/processing/path_helpers.py
noiz/processing/ppsd.py
noiz/processing/qc.py
noiz/processing/signal_helpers.py
noiz/processing/signal_utils.py
noiz/processing/stacking.py
noiz/processing/time_utils.py
noiz/processing/timeseries.py
noiz/processing/timespan.py
noiz/processing/warning_handling.py
noiz/processing/obspy_derived/__init__.py
noiz/processing/obspy_derived/array_analysis.py
noiz/processing/soh/__init__.py
noiz/processing/soh/parsing.py
noiz/processing/soh/parsing_params.py
noiz/processing/soh/plotting.py
noiz/processing/soh/transformation.py
noiz-0.7.1.dist-info/METADATA
noiz-0.7.1.dist-info/WHEEL
noiz-0.7.1.dist-info/entry_points.txt
noiz-0.7.1.dist-info/licenses/LICENSE.rst
noiz-0.7.1.dist-info/RECORD
