Metadata-Version: 2.4
Name: noiz
Version: 0.7.1
Project-URL: Homepage, https://noiz-group.gitlab.io/
Project-URL: Documentation, https://noiz-group.gitlab.io/noiz/
Project-URL: Repository, https://gitlab.com/noiz-group/noiz.git
Project-URL: Changelog, https://gitlab.com/noiz-group/noiz/-/blob/master/CHANGELOG.rst
Author-email: Damian Kula <heavelock@gmail.com>, Alexandre Kazantsev <alexandre.kazantsev@storengy.com>, Arthur Dartois <arthur.dartois@storengy.com>, Laure Duboeuf <laure.duboeuf@external.storengy.com>
License: CECILL-B
License-File: LICENSE.rst
Classifier: Development Status :: 4 - Beta
Classifier: License :: CeCILL-B Free Software License Agreement (CECILL-B)
Classifier: Programming Language :: Python :: 3.9
Classifier: Programming Language :: Python :: 3.10
Classifier: Topic :: Scientific/Engineering
Requires-Python: <3.11,>=3.10
Requires-Dist: click>=8.0.3
Requires-Dist: dask[complete]==2021.11.2
Requires-Dist: environs>=9.3.5
Requires-Dist: flask-migrate==3.1.0
Requires-Dist: flask-sqlalchemy==2.5.1
Requires-Dist: flask==2.0.2
Requires-Dist: loguru>=0.5.3
Requires-Dist: matplotlib==3.5.0
Requires-Dist: more-itertools>=8.11
Requires-Dist: numpy==1.23.5
Requires-Dist: obspy==1.4.2
Requires-Dist: pandas==1.3.4
Requires-Dist: pendulum~=3.0
Requires-Dist: psycopg2-binary==2.9.2
Requires-Dist: pydantic~=1.8
Requires-Dist: scipy<2.0,>=1.13.0
Requires-Dist: sqlalchemy<2.0,>=1.4.0
Requires-Dist: toml>=0.10.2
Requires-Dist: tqdm>=4.62.3
Requires-Dist: utm>=0.7.0
Requires-Dist: werkzeug==2.3.3
